kthread_sleep/LICENSE
kthread_sleep/README.MD
kthread_sleep/__init__.py
kthread_sleep/requirements.txt
kthread_sleep/thirdparty.json
kthread_sleep-0.11.dist-info/LICENSE.rst
kthread_sleep-0.11.dist-info/METADATA
kthread_sleep-0.11.dist-info/WHEEL
kthread_sleep-0.11.dist-info/top_level.txt
kthread_sleep-0.11.dist-info/RECORD
